{
  "address1": "885 West Georgia Street",
  "address2": "Suite 1500",
  "city": "Vancouver",
  "state": "BC",
  "zip": "V6C 3E8",
  "country": "Canada",
  "phone": "604 895 2700",
  "website": "https://www.westfraser.com",
  "industry": "Lumber & Wood Production",
  "industryKey": "lumber-wood-production",
  "industryDisp": "Lumber & Wood Production",
  "sector": "Basic Materials",
  "sectorKey": "basic-materials",
  "sectorDisp": "Basic Materials",
  "longBusinessSummary": "West Fraser Timber Co. Ltd., a diversified wood products company, engages in manufacturing, selling, marketing, and distributing lumber, engineered wood products, pulp, newsprint, wood chips, and other residuals and renewable energy. It offers spruce-pine-fir, douglas fir-larch, hem-fir, and southern yellow pine lumber, treated wood products, medium density fiberboard panels and plywood, oriented strand board, and laminated veneer lumber wood products, as well as particleboards. In addition, the company provides northern bleached softwood Kraft pulp and bleached chemical thermo-mechanical pulp used to produce various paper products, including printing and writing papers, paperboard products, tissue and towel products, and a variety of other paper grades. Further, it offers bioproducts, including bioenergy and biomaterial. Its products are used in home construction, repair and remodeling, papers, tissue, and box materials, and industrial applications. The company sells its products to major retail chains, contractor supply yards, and wholesalers, as well as industrial customers for further processing or as components for other products in Canada, the United States, the United Kingdom, Europe, and internationally. West Fraser Timber Co. Ltd. was founded in 1955 and is headquartered in Vancouver, Canada.",
  "fullTimeEmployees": 9700,
  "companyOfficers": [
    {
      "maxAge": 1,
      "name": "Mr. Sean P. McLaren",
      "age": 55,
      "title": "CEO, President & Director",
      "yearBorn": 1969,
      "fiscalYear": 2024,
      "totalPay": 1218545,
      "exercisedValue": 0,
      "unexercisedValue": 1365139
    },
    {
      "maxAge": 1,
      "name": "Mr. Christopher A. Virostek CA, CPA, HBBA",
      "age": 51,
      "title": "Senior VP of Finance & CFO",
      "yearBorn": 1973,
      "fiscalYear": 2024,
      "totalPay": 600750,
      "exercisedValue": 0,
      "unexercisedValue": 1333428
    },
    {
      "maxAge": 1,
      "name": "Ms. Robin A. Lampard",
      "age": 57,
      "title": "Senior Vice-President of Corporate Services",
      "yearBorn": 1967,
      "fiscalYear": 2024,
      "totalPay": 519250,
      "exercisedValue": 0,
      "unexercisedValue": 435862
    },
    {
      "maxAge": 1,
      "name": "Mr. Kevin John Burke",
      "title": "Executive Vice-President of North American Operations",
      "fiscalYear": 2024,
      "totalPay": 872849,
      "exercisedValue": 0,
      "unexercisedValue": 285823
    },
    {
      "maxAge": 1,
      "name": "Mr. Alan G. McMeekin",
      "age": 56,
      "title": "Senior Vice President of Europe",
      "yearBorn": 1968,
      "fiscalYear": 2024,
      "totalPay": 602018,
      "exercisedValue": 0,
      "unexercisedValue": 576040
    },
    {
      "maxAge": 1,
      "name": "Mr. Chuck H. Watkins",
      "title": "Vice-President of Capital & Technology",
      "fiscalYear": 2024,
      "exercisedValue": 0,
      "unexercisedValue": 0
    },
    {
      "maxAge": 1,
      "name": "Mr. Robert B. Winslow C.F.A.",
      "title": "Director of Investor Relations & Corporate Development",
      "fiscalYear": 2024,
      "exercisedValue": 0,
      "unexercisedValue": 0
    },
    {
      "maxAge": 1,
      "name": "Ms. Shannon D. Webber LL.B",
      "title": "VP & General Counsel",
      "fiscalYear": 2024,
      "exercisedValue": 0,
      "unexercisedValue": 0
    },
    {
      "maxAge": 1,
      "name": "Mr. Matthew Vincent Tobin",
      "title": "Senior Vice President of Sales & Marketing",
      "fiscalYear": 2024,
      "exercisedValue": 0,
      "unexercisedValue": 0
    },
    {
      "maxAge": 1,
      "name": "Mr. Alan Anthony Caputo",
      "title": "Vice President of Human Resources",
      "fiscalYear": 2024,
      "exercisedValue": 0,
      "unexercisedValue": 0
    }
  ],
  "auditRisk": 5,
  "boardRisk": 3,
  "compensationRisk": 6,
  "shareHolderRightsRisk": 1,
  "overallRisk": 3,
  "governanceEpochDate": 1759276800,
  "compensationAsOfEpochDate": 1735603200,
  "irWebsite": "http://www.westfraser.com/ir/index.asp",
  "executiveTeam": [],
  "maxAge": 86400,
  "priceHint": 2,
  "previousClose": 95.32,
  "open": 95.04,
  "dayLow": 94.91,
  "dayHigh": 96.82,
  "regularMarketPreviousClose": 95.32,
  "regularMarketOpen": 95.04,
  "regularMarketDayLow": 94.91,
  "regularMarketDayHigh": 96.82,
  "dividendRate": 1.78,
  "dividendYield": 1.87,
  "exDividendDate": 1758758400,
  "payoutRatio": 0.72190005,
  "fiveYearAvgDividendYield": 1.31,
  "beta": 1.308,
  "forwardPE": 13.741008,
  "volume": 113438,
  "regularMarketVolume": 113438,
  "averageVolume": 323484,
  "averageVolume10days": 208330,
  "averageDailyVolume10Day": 208330,
  "bid": 95.44,
  "ask": 95.53,
  "marketCap": 7531165184,
  "fiftyTwoWeekLow": 92.48,
  "fiftyTwoWeekHigh": 141.27,
  "allTimeHigh": 141.27,
  "allTimeLow": 4.81214,
  "priceToSalesTrailing12Months": 1.291352,
  "fiftyDayAverage": 99.54,
  "twoHundredDayAverage": 107.7635,
  "trailingAnnualDividendRate": 1.28,
  "trailingAnnualDividendYield": 0.0134284515,
  "currency": "CAD",
  "tradeable": false,
  "enterpriseValue": 7220905472,
  "profitMargins": -0.0216,
  "floatShares": 75350849,
  "sharesOutstanding": 76578891,
  "sharesShort": 1467606,
  "sharesShortPriorMonth": 648106,
  "sharesShortPreviousMonthDate": 1755216000,
  "dateShortInterest": 1757894400,
  "sharesPercentSharesOut": 0.0186,
  "heldPercentInsiders": 0.32179,
  "heldPercentInstitutions": 0.51585,
  "shortRatio": 3.16,
  "impliedSharesOutstanding": 78860369,
  "bookValue": 87.341,
  "priceToBook": 1.0934154,
  "lastFiscalYearEnd": 1735603200,
  "nextFiscalYearEnd": 1767139200,
  "mostRecentQuarter": 1750982400,
  "netIncomeToCommon": -126000000,
  "trailingEps": -2.24,
  "forwardEps": 6.95,
  "lastSplitFactor": "2:1",
  "lastSplitDate": 1389657600,
  "enterpriseToRevenue": 1.238,
  "enterpriseToEbitda": 15.462,
  "52WeekChange": -0.2778828,
  "SandP52WeekChange": 0.17904854,
  "lastDividendValue": 0.445,
  "lastDividendDate": 1758758400,
  "quoteType": "EQUITY",
  "currentPrice": 95.5,
  "targetHighPrice": 119.82866,
  "targetLowPrice": 117.700195,
  "targetMeanPrice": 118.76443,
  "targetMedianPrice": 118.76443,
  "recommendationKey": "none",
  "numberOfAnalystOpinions": 2,
  "totalCash": 646000000,
  "totalCashPerShare": 8.192,
  "ebitda": 467000000,
  "totalDebt": 336000000,
  "quickRatio": 1.516,
  "currentRatio": 2.889,
  "totalRevenue": 5832000000,
  "debtToEquity": 4.871,
  "revenuePerShare": 73.034,
  "returnOnAssets": -0.00504,
  "returnOnEquity": -0.017819999,
  "grossProfits": 1619000064,
  "freeCashflow": 68000000,
  "operatingCashflow": 533000000,
  "revenueGrowth": -0.101,
  "grossMargins": 0.27761,
  "ebitdaMargins": 0.08008,
  "operatingMargins": -0.02937,
  "financialCurrency": "USD",
  "symbol": "WFG.TO",
  "language": "en-US",
  "region": "US",
  "typeDisp": "Equity",
  "quoteSourceName": "Delayed Quote",
  "triggerable": true,
  "customPriceAlertConfidence": "HIGH",
  "corporateActions": [],
  "regularMarketTime": 1759521600,
  "exchange": "TOR",
  "messageBoardId": "finmb_643621",
  "exchangeTimezoneName": "America/Toronto",
  "exchangeTimezoneShortName": "EDT",
  "gmtOffSetMilliseconds": -14400000,
  "market": "ca_market",
  "esgPopulated": false,
  "marketState": "CLOSED",
  "longName": "West Fraser Timber Co. Ltd.",
  "regularMarketChange": 0.1800003,
  "regularMarketDayRange": "94.91 - 96.82",
  "fullExchangeName": "Toronto",
  "averageDailyVolume3Month": 323484,
  "fiftyTwoWeekLowChange": 3.0199966,
  "fiftyTwoWeekLowChangePercent": 0.03265567,
  "fiftyTwoWeekRange": "92.48 - 141.27",
  "fiftyTwoWeekHighChange": -45.770004,
  "fiftyTwoWeekHighChangePercent": -0.32398954,
  "fiftyTwoWeekChangePercent": -27.78828,
  "dividendDate": 1760400000,
  "earningsTimestamp": 1761163200,
  "earningsTimestampStart": 1761163200,
  "earningsTimestampEnd": 1761163200,
  "earningsCallTimestampStart": 1761233400,
  "earningsCallTimestampEnd": 1761233400,
  "isEarningsDateEstimate": false,
  "epsTrailingTwelveMonths": -2.24,
  "epsForward": 6.95,
  "epsCurrentYear": -1.31898,
  "priceEpsCurrentYear": -72.404434,
  "fiftyDayAverageChange": -4.040001,
  "fiftyDayAverageChangePercent": -0.040586706,
  "twoHundredDayAverageChange": -12.263496,
  "twoHundredDayAverageChangePercent": -0.1138001,
  "sourceInterval": 15,
  "exchangeDataDelayedBy": 15,
  "cryptoTradeable": false,
  "hasPrePostMarketData": false,
  "firstTradeDateMilliseconds": 515856600000,
  "shortName": "WEST FRASER TIMBER CO LTD",
  "regularMarketChangePercent": 0.18883792,
  "regularMarketPrice": 95.5,
  "trailingPegRatio": null
}